setup.py
afgutils/__init__.py
afgutils/advanceai_util.py
afgutils/cgi.py
afgutils/credolab.py
afgutils/db.py
afgutils/email.py
afgutils/s3.py
afgutils/trandata.py
afgutils/utils.py
afgutils.egg-info/PKG-INFO
afgutils.egg-info/SOURCES.txt
afgutils.egg-info/dependency_links.txt
afgutils.egg-info/requires.txt
afgutils.egg-info/top_level.txt