Metadata-Version: 2.1
Name: afgutils
Version: 1.2.0
Summary: Shared support functions
Author: Araz Heydarov
Author-email: araz.heydarov@asiafinancegroup.com
License: copyright
Requires-Python: >=3.10
Requires-Dist: requests>=2.31.0
Requires-Dist: pyodbc>=4.0.39
Requires-Dist: pywin32>=306
Requires-Dist: python-dotenv>=1.0.0
Requires-Dist: boto3>=1.27.0
Requires-Dist: pandas>=2.0.3
Requires-Dist: xmltodict>=0.13.0
